pymdlj/__init__.py
pymdlj/pymdlj.cpython-35m-x86_64-linux-gnu.so
pymdlj.libs/libgomp-f7e03b3e.so.1.0.0
pymdlj.libs/libboost_regex-899748ab.so.5
pymdlj.libs/libicuuc-8a9b26fa.so.42.1
pymdlj.libs/libicudata-13dff365.so.42.1
pymdlj.libs/libicui18n-6ab72f54.so.42.1
pymdlj-0.1.0.dist-info/top_level.txt
pymdlj-0.1.0.dist-info/RECORD
pymdlj-0.1.0.dist-info/METADATA
pymdlj-0.1.0.dist-info/WHEEL
