Metadata-Version: 2.1
Name: pymdlj
Version: 0.1.0
Summary: Python package for performing MD simulations using Lennard-Jones potentials
Home-page: https://github.com/ifilot/pymdlj
Author: Ivo Filot
Author-email: ivo@ivofilot.nl
License: UNKNOWN
Platform: UNKNOWN
Classifier: Programming Language :: Python :: 3
Classifier: License :: OSI Approved :: MIT License
Classifier: Operating System :: POSIX
Requires-Python: >=3.5
Requires-Dist: numpy
